crescendo/__init__.py
crescendo/analysis.py
crescendo/entrypoint.py
crescendo/logger.py
crescendo/_tests/__init__.py
crescendo/_tests/conftest.py
crescendo/_tests/test_data.py
crescendo/configs/LICENSE
crescendo/configs/README.md
crescendo/configs/__init__.py
crescendo/configs/train.yaml
crescendo/configs/callbacks/default.yaml
crescendo/configs/data/california_housing.yaml
crescendo/configs/data/common_data.yaml
crescendo/configs/data/regression.yaml
crescendo/configs/debug/default.yaml
crescendo/configs/debug/fdr.yaml
crescendo/configs/debug/limit.yaml
crescendo/configs/debug/overfit.yaml
crescendo/configs/debug/profiler.yaml
crescendo/configs/experiment/example.yaml
crescendo/configs/extras/default.yaml
crescendo/configs/hparams_search/optuna.yaml
crescendo/configs/hydra/default.yaml
crescendo/configs/logger/aim.yaml
crescendo/configs/logger/comet.yaml
crescendo/configs/logger/csv.yaml
crescendo/configs/logger/many_loggers.yaml
crescendo/configs/logger/mlflow.yaml
crescendo/configs/logger/neptune.yaml
crescendo/configs/logger/tensorboard.yaml
crescendo/configs/logger/wandb.yaml
crescendo/configs/model/README.md
crescendo/configs/model/common_model.yaml
crescendo/configs/model/mlp.yaml
crescendo/configs/model/mlp_default.yaml
crescendo/configs/model/mlp_random_architecture.yaml
crescendo/configs/paths/default.yaml
crescendo/configs/trainer/cpu.yaml
crescendo/configs/trainer/ddp.yaml
crescendo/configs/trainer/ddp_sim.yaml
crescendo/configs/trainer/default.yaml
crescendo/configs/trainer/gpu.yaml
crescendo/configs/trainer/mps.yaml
crescendo/data/__init__.py
crescendo/data/_common.py
crescendo/data/array.py
crescendo/models/__init__.py
crescendo/models/mlp.py
crescendo/utils/README.md
crescendo/utils/__init__.py
crescendo/utils/datasets.py
crescendo/utils/instantiators.py
crescendo/utils/modifiers.py
crescendo/utils/other_utils.py
crescendo-0.0.4.dist-info/entry_points.txt
crescendo-0.0.4.dist-info/LICENSE
crescendo-0.0.4.dist-info/WHEEL
crescendo-0.0.4.dist-info/METADATA
crescendo-0.0.4.dist-info/RECORD
