Metadata-Version: 2.1
Name: crescendo
Version: 0.0.4
Summary: Machine learning made easy
Author-email: "Matthew R. Carbone" <mcarbone@bnl.gov>
Maintainer-email: "Matthew R. Carbone" <mcarbone@bnl.gov>
Requires-Python: >=3.9
Classifier: Development Status :: 2 - Pre-Alpha
Classifier: Natural Language :: English
Classifier: Programming Language :: Python :: 3 :: Only
Classifier: Programming Language :: Python :: 3.9
Classifier: Programming Language :: Python :: 3
Classifier: Topic :: Scientific/Engineering
Classifier: Intended Audience :: Developers
Classifier: Intended Audience :: Education
Classifier: Intended Audience :: Science/Research
Requires-Dist: torch==2.0.0
Requires-Dist: torchvision==0.15.1
Requires-Dist: lightning==2.0.2
Requires-Dist: torchmetrics==0.11.4
Requires-Dist: hydra-core==1.3.2
Requires-Dist: hydra-colorlog==1.2.0
Requires-Dist: hydra-optuna-sweeper==1.2.0
Requires-Dist: pymatgen==2023.9.10
Requires-Dist: matgl==0.8.5
Requires-Dist: pandas
Requires-Dist: numpy
Requires-Dist: scikit-learn
Requires-Dist: rich
Requires-Dist: loguru
Requires-Dist: sphinx ; extra == "doc"
Requires-Dist: numpydoc ; extra == "doc"
Requires-Dist: sphinx-copybutton ; extra == "doc"
Requires-Dist: sphinx_rtd_theme ; extra == "doc"
Requires-Dist: ipython ; extra == "doc"
Requires-Dist: matplotlib ; extra == "doc"
Requires-Dist: coverage ; extra == "test"
Requires-Dist: flake8 ; extra == "test"
Requires-Dist: pytest ; extra == "test"
Requires-Dist: pytest-cov ; extra == "test"
Requires-Dist: black ; extra == "test"
Requires-Dist: nbstripout ; extra == "test"
Requires-Dist: pre-commit ; extra == "test"
Provides-Extra: doc
Provides-Extra: test
